{"dataset_name": "did2-qzw3", "columns": [{"column_name": "CEQR", "number_non_empty_cells": 33203, "number_empty_cells": 0, "number_distinct_values": 9683, "frequent_values": ["00DCP034Y", "95DCP052Q", "14HPD088K", "19HPD045X", "15DME009Y"], "data_types": {"type": "TEXT", "count": 33203, "shortest_values": ["79-069M", "80-044X", "82-070M", "82-212M", "82-248K"], "longest_values": ["00DCLA001Q", "00DCLA001R", "02DCLA001K", "03DCLA001Q", "03DCLA001X"], "average_length": 8.97533355419691}}, {"column_name": "Project Name", "number_non_empty_cells": 33203, "number_empty_cells": 0, "number_distinct_values": 9289, "frequent_values": ["Unified Bulk Program and Related Zoning Map Text Amendments", "Downtown Flushing Rezoning", "MHANY 2", "Langsam 16", "Citywide Ferry Service"], "data_types": {"type": "TEXT", "count": 33203, "shortest_values": ["BBQ", "CEVF", "Yelo", "Ajune", "Bania"], "longest_values": ["Acquisition & Disposition of Property Between The City of NY and Mann Enterprises In Conjunction with Remediation of the Brookfield Avenue Landfill", "Restricted Use Street Designation for Fashion Institute  of Technology New Additions, Streetscapes, Renovations, and Refunding Project", "Rockaway Water Pollution Control Plant-Installation of Natural Gas Service and Removal of Underground Petroleum Bulk Storage", "Bushwick East: 203-207 Palmetto Street; 11 Dodworth Street, 84 Stanhope Street, 103 Bleeker Street; and 1175 Greene Avenue", "Waste Management of New York, LLC. Putrescible Solid Waste Transfer Station Permit Modification to Increase Storage Volume"], "average_length": 29.296057585157968}}, {"column_name": "Block", "number_non_empty_cells": 33203, "number_empty_cells": 0, "number_distinct_values": 5509, "frequent_values": ["None", "1900", "7775", "177", "7577"], "data_types": {"type": "INTEGER", "count": 33203, "min_value": 0, "max_value": 133363, "mean": 3410.0168417184905, "stddev": 3551.392249004705}}, {"column_name": "Lot", "number_non_empty_cells": 33203, "number_empty_cells": 0, "number_distinct_values": 913, "frequent_values": ["1", "None", "5", "20", "6"], "data_types": {"type": "INTEGER", "count": 33203, "min_value": 0, "max_value": 165168, "mean": 172.0063023905624, "stddev": 1705.963018315731}}, {"column_name": "Community District", "number_non_empty_cells": 33203, "number_empty_cells": 0, "number_distinct_values": 85, "frequent_values": ["SI03", "MN04", "MN02", "QN07", "BK02"], "data_types": {"type": "TEXT", "count": 33203, "shortest_values": ["N/A", "n/a", "BK01", "BK02", "BK03"], "longest_values": ["BK/all", "BX/all", "Bk/all", "BK01", "BK02"], "average_length": 3.99954823359335}}, {"column_name": "House Number", "number_non_empty_cells": 33203, "number_empty_cells": 0, "number_distinct_values": 1158, "frequent_values": ["None", "1", "150", "25", "760"], "data_types": {"type": "TEXT", "count": 33203, "shortest_values": ["1", "2", "3", "4", "5"], "longest_values": ["1388 EAST", "1113-113", "163 WEST", "3337-347", "130-138"], "average_length": 3.97524320091558}}, {"column_name": "Street Name", "number_non_empty_cells": 33203, "number_empty_cells": 0, "number_distinct_values": 1450, "frequent_values": ["None", "BROADWAY", "NORTHERN BOULEVARD", "RICHMOND AVENUE", "MADISON AVENUE"], "data_types": {"type": "TEXT", "count": 33203, "shortest_values": ["ALL", "LIE", "N/A", "None", "890/65"], "longest_values": ["100 FEET WEST OF ADAM CLAYTON PO", "1006 &1024 CRESCENT STREET, 701-", "10315 FARRAGUT ROAD, CORNER OF E", "104-04 DITMARS BOULEVARD, BETWEE", "1052 EAST 26TH STREET, BETWEEN A"], "average_length": 5.064452007348733}}, {"column_name": "Postcode", "number_non_empty_cells": 33203, "number_empty_cells": 0, "number_distinct_values": 172, "frequent_values": ["None", "10013", "11205", "11211", "11206"], "data_types": {"type": "TEXT", "count": 33203, "shortest_values": ["None", "10001", "10002", "10003", "10004"], "longest_values": ["10001", "10002", "10003", "10004", "10005"], "average_length": 4.052736198536277}}], "key_column_candidates": []}