{"dataset_name": "edai-t99u", "columns": [{"column_name": "GRADE LEVEL", "number_non_empty_cells": 514, "number_empty_cells": 0, "number_distinct_values": 15, "frequent_values": ["MS Core", "09-12", "0K-09", "02", "03"], "data_types": {"type": "TEXT", "count": 514, "shortest_values": ["01", "02", "03", "04", "05"], "longest_values": ["(MS CORE and ", "(K-9* ONLY)\"", "9-12 ONLY)\"", "MS Core", "09-12"], "average_length": 4.4319066147859925}}, {"column_name": "PROGRAM TYPE", "number_non_empty_cells": 513, "number_empty_cells": 1, "number_distinct_values": 6, "frequent_values": ["GEN ED / CTT / G&T", "GEN ED / CTT", "SPEC ED", null, "\"SERVICE CATEGORY"], "data_types": {"type": "TEXT", "count": 514, "shortest_values": ["SPEC ED", "CLASS SIZE", "GEN ED / CTT", "\"SERVICE CATEGORY", "GEN ED / CTT / G&T"], "longest_values": ["GEN ED / CTT / G&T", "\"SERVICE CATEGORY", "GEN ED / CTT", "CLASS SIZE", "SPEC ED"], "average_length": 12.922027290448343}}, {"column_name": "\"CORE SUBJECT ", "number_non_empty_cells": 512, "number_empty_cells": 2, "number_distinct_values": 7, "frequent_values": ["-", "English/ESL", "Mathematics", "Science", "Social Studies"], "data_types": {"type": "TEXT", "count": 514, "shortest_values": ["-", "Science", "English/ESL", "Mathematics", "Social Studies"], "longest_values": ["NUMBER OF CLASSES", "Social Studies", "English/ESL", "Mathematics", "Science"], "average_length": 6.2109375}}], "key_column_candidates": []}