{"dataset_name": "nu7n-tubp", "columns": [{"column_name": "RowNumber", "number_non_empty_cells": 345727, "number_empty_cells": 0, "number_distinct_values": 117371, "frequent_values": ["2007", "2914", "4330", "4753", "5515"], "data_types": {"type": "INTEGER", "count": 345727, "min_value": 1, "max_value": 117371, "mean": 54971.56195261218, "stddev": 32103.886915760555}}, {"column_name": "AnimalName", "number_non_empty_cells": 345727, "number_empty_cells": 0, "number_distinct_values": 22263, "frequent_values": ["UNKNOWN", "BELLA", "NAME NOT PROVIDED", "MAX", "CHARLIE"], "data_types": {"type": "TEXT", "count": 345727, "shortest_values": ["-", "2", "A", "B", "C"], "longest_values": ["BUDEREAUXBUDERONIMUSBUDEROWSKI", "CARLYAPPLEWHITECRAWFORDCOLEMAN", "JEFFERSONBARNARDRAMSEYDONNELLY", "PIPLONGFELLOWBUTTERFIELDFROUDE", "SAMSONMAXWELLWALTERZANE(SAMMY)"], "average_length": 5.459926473778443}}, {"column_name": "AnimalGender", "number_non_empty_cells": 345727, "number_empty_cells": 0, "number_distinct_values": 3, "frequent_values": ["M", "F", "None"], "data_types": {"type": "TEXT", "count": 345727, "shortest_values": ["F", "M", "None"], "longest_values": ["None", "F", "M"], "average_length": 1.000156192602834}}, {"column_name": "AnimalBirthMonth", "number_non_empty_cells": 345727, "number_empty_cells": 0, "number_distinct_values": 61, "frequent_values": ["2016", "2015", "2014", "2013", "2012"], "data_types": {"type": "INTEGER", "count": 345727, "min_value": 1, "max_value": 2018, "mean": 2011.2785319052225, "stddev": 14.781604511937136}}, {"column_name": "BreedName", "number_non_empty_cells": 345727, "number_empty_cells": 0, "number_distinct_values": 319, "frequent_values": ["Unknown", "Yorkshire Terrier", "Shih Tzu", "Chihuahua", "Maltese"], "data_types": {"type": "TEXT", "count": 345727, "shortest_values": ["Pug", "Mudi", "Puli", "Pumi", "Tosa"], "longest_values": ["American Pit Bull Mix / Pit Bull Mix", "Mastiff, French (Dogue de Bordeaux)", "American Pit Bull Terrier/Pit Bull", "Nova Scotia Duck Tolling Retriever", "Dachshund, Long Haired Miniature"], "average_length": 15.03413676108606}}, {"column_name": "Borough", "number_non_empty_cells": 345727, "number_empty_cells": 0, "number_distinct_values": 1, "frequent_values": ["None"], "data_types": {"type": "TEXT", "count": 345727, "shortest_values": ["None"], "longest_values": ["None"], "average_length": 4.0}}, {"column_name": "ZipCode", "number_non_empty_cells": 345727, "number_empty_cells": 0, "number_distinct_values": 529, "frequent_values": ["10025", "10023", "10024", "10011", "11201"], "data_types": {"type": "INTEGER", "count": 345727, "min_value": 121, "max_value": 99508, "mean": 10694.652326835996, "stddev": 1218.2186774201984}}, {"column_name": "LicenseIssuedDate", "number_non_empty_cells": 345727, "number_empty_cells": 0, "number_distinct_values": 1571, "frequent_values": ["09/13/2017", "07/12/2016", "09/06/2017", "08/08/2016", "08/09/2016"], "data_types": {"type": "DATE/TIME", "count": 345727, "min_value": "09/12/2014", "max_value": "12/31/2018"}}, {"column_name": "LicenseExpiredDate", "number_non_empty_cells": 345727, "number_empty_cells": 0, "number_distinct_values": 2987, "frequent_values": ["07/30/2017", "08/30/2017", "05/30/2017", "06/29/2017", "08/30/2018"], "data_types": {"type": "DATE/TIME", "count": 345727, "min_value": "01/01/2016", "max_value": "11/29/2028"}}, {"column_name": "Extract Year", "number_non_empty_cells": 345727, "number_empty_cells": 0, "number_distinct_values": 3, "frequent_values": ["2018", "2017", "2016"], "data_types": {"type": "INTEGER", "count": 345727, "min_value": 2016, "max_value": 2018, "mean": 2017.0134557034912, "stddev": 0.8156862478231228}}], "key_column_candidates": []}