{"dataset_name": "yuzm-c784", "columns": [{"column_name": "DBN", "number_non_empty_cells": 67639, "number_empty_cells": 0, "number_distinct_values": 1139, "frequent_values": ["20K104", "17K138", "03M333", "26Q266", "10X020"], "data_types": {"type": "TEXT", "count": 67639, "shortest_values": ["01M015", "01M019", "01M020", "01M034", "01M063"], "longest_values": ["01M015", "01M019", "01M020", "01M034", "01M063"], "average_length": 6.0}}, {"column_name": "Grade", "number_non_empty_cells": 67639, "number_empty_cells": 0, "number_distinct_values": 7, "frequent_values": ["All Grades", "3", "4", "5", "6"], "data_types": {"type": "INTEGER", "count": 67639, "min_value": 3, "max_value": 8, "mean": 5.153014296984726, "stddev": 1.6545746399975445}}, {"column_name": "Year", "number_non_empty_cells": 67639, "number_empty_cells": 0, "number_distinct_values": 7, "frequent_values": ["2010", "2012", "2011", "2009", "2008"], "data_types": {"type": "INTEGER", "count": 67639, "min_value": 2006, "max_value": 2012, "mean": 2009.0843891837487, "stddev": 1.9763766455905878}}, {"column_name": "Demographic", "number_non_empty_cells": 67639, "number_empty_cells": 0, "number_distinct_values": 2, "frequent_values": ["Male", "Female"], "data_types": {"type": "TEXT", "count": 67639, "shortest_values": ["Male", "Female"], "longest_values": ["Female", "Male"], "average_length": 4.97550229896953}}, {"column_name": "Number Tested", "number_non_empty_cells": 67639, "number_empty_cells": 0, "number_distinct_values": 811, "frequent_values": ["1", "31", "34", "36", "35"], "data_types": {"type": "INTEGER", "count": 67639, "min_value": 1, "max_value": 1225, "mean": 82.89668682269104, "stddev": 95.78049947515515}}, {"column_name": "Mean Scale Score", "number_non_empty_cells": 56453, "number_empty_cells": 11186, "number_distinct_values": 202, "frequent_values": ["", "s", "658", "657", "655"], "data_types": {"type": "INTEGER", "count": 67639, "min_value": 526, "max_value": 752, "mean": 658.3637539974611, "stddev": 17.75916738241833}}, {"column_name": "Num Level 1", "number_non_empty_cells": 67639, "number_empty_cells": 0, "number_distinct_values": 159, "frequent_values": ["0", "1", "2", "3", "4"], "data_types": {"type": "INTEGER", "count": 67639, "min_value": 0, "max_value": 292, "mean": 8.127540218516874, "stddev": 12.731281462560617}}, {"column_name": "Pct Level 1", "number_non_empty_cells": 67639, "number_empty_cells": 0, "number_distinct_values": 727, "frequent_values": ["0", "s", "2.9", "16.7", "14.3"], "data_types": {"type": "REAL", "count": 67639, "min_value": 0.0, "max_value": 100.0, "mean": 10.546641116382581, "stddev": 12.50805861945446}}, {"column_name": "Num Level 2", "number_non_empty_cells": 67639, "number_empty_cells": 0, "number_distinct_values": 410, "frequent_values": ["s", "9", "12", "13", "11"], "data_types": {"type": "INTEGER", "count": 67639, "min_value": 0, "max_value": 609, "mean": 32.73348375032814, "stddev": 41.91283762846526}}, {"column_name": "Pct Level 2", "number_non_empty_cells": 67639, "number_empty_cells": 0, "number_distinct_values": 863, "frequent_values": ["s", "50", "33.3", "0", "25"], "data_types": {"type": "REAL", "count": 67639, "min_value": 0.0, "max_value": 100.0, "mean": 37.708170424516304, "stddev": 17.62406799813263}}, {"column_name": "Num Level 3", "number_non_empty_cells": 67639, "number_empty_cells": 0, "number_distinct_values": 516, "frequent_values": ["s", "13", "10", "11", "16"], "data_types": {"type": "INTEGER", "count": 67639, "min_value": 0, "max_value": 681, "mean": 41.38977576534919, "stddev": 52.06002849174971}}, {"column_name": "Pct Level 3", "number_non_empty_cells": 67639, "number_empty_cells": 0, "number_distinct_values": 949, "frequent_values": ["s", "50", "66.7", "33.3", "0"], "data_types": {"type": "REAL", "count": 67639, "min_value": 0.0, "max_value": 100.0, "mean": 46.822927258959496, "stddev": 20.160356796710822}}, {"column_name": "Num Level 4", "number_non_empty_cells": 67639, "number_empty_cells": 0, "number_distinct_values": 136, "frequent_values": ["0", "1", "2", "3", "4"], "data_types": {"type": "INTEGER", "count": 67639, "min_value": 0, "max_value": 215, "mean": 4.299973728538563, "stddev": 8.909810638676653}}, {"column_name": "Pct Level 4", "number_non_empty_cells": 67639, "number_empty_cells": 0, "number_distinct_values": 563, "frequent_values": ["0", "s", "2.9", "2", "2.4"], "data_types": {"type": "REAL", "count": 67639, "min_value": 0.0, "max_value": 92.6, "mean": 4.923910120694205, "stddev": 7.622124162133327}}, {"column_name": "Num Level 3 and 4", "number_non_empty_cells": 67639, "number_empty_cells": 0, "number_distinct_values": 565, "frequent_values": ["s", "13", "11", "10", "16"], "data_types": {"type": "INTEGER", "count": 67639, "min_value": 0, "max_value": 767, "mean": 45.691047613160514, "stddev": 58.08806742083632}}, {"column_name": "Pct Level 3 and 4", "number_non_empty_cells": 67639, "number_empty_cells": 0, "number_distinct_values": 989, "frequent_values": ["s", "50", "0", "100", "66.7"], "data_types": {"type": "REAL", "count": 67639, "min_value": 0.0, "max_value": 100.0, "mean": 51.74662257182141, "stddev": 23.80222289115036}}], "key_column_candidates": []}